[
  {
    "id": "4fe7b33d5ff3894550c8b10721b121cc",
    "sport_key": "basketball_ncaab",
    "sport_title": "NCAAB",
    "commence_time": "2025-11-28T03:55:00Z",
    "home_team": "Northwestern Wildcats",
    "away_team": "Oklahoma St Cowboys",
    "bookmakers": [
      {
        "key": "gtbets",
        "title": "GTbets",
        "last_update": "2025-11-28T06:07:56Z",
        "markets": [
          {
            "key": "h2h",
            "last_update": "2025-11-28T06:07:56Z",
            "outcomes": [
              {
                "name": "Northwestern Wildcats",
                "price": 6
              },
              {
                "name": "Oklahoma St Cowboys",
                "price": 1.12
              }
            ]
          }
        ]
      },
      {
        "key": "pinnacle",
        "title": "Pinnacle",
        "last_update": "2025-11-28T06:10:10Z",
        "markets": [
          {
            "key": "h2h",
            "last_update": "2025-11-28T06:10:10Z",
            "outcomes": [
              {
                "name": "Northwestern Wildcats",
                "price": 6.7
              },
              {
                "name": "Oklahoma St Cowboys",
                "price": 1.1
              }
            ]
          }
        ]
      },
      {
        "key": "unibet_nl",
        "title": "Unibet (NL)",
        "last_update": "2025-11-28T06:01:42Z",
        "markets": [
          {
            "key": "h2h",
            "last_update": "2025-11-28T06:01:42Z",
            "outcomes": [
              {
                "name": "Northwestern Wildcats",
                "price": 4
              },
              {
                "name": "Oklahoma St Cowboys",
                "price": 1.23
              }
            ]
          }
        ]
      },
      {
        "key": "nordicbet",
        "title": "Nordic Bet",
        "last_update": "2025-11-28T05:58:24Z",
        "markets": [
          {
            "key": "h2h",
            "last_update": "2025-11-28T05:58:24Z",
            "outcomes": [
              {
                "name": "Northwestern Wildcats",
                "price": 4.3
              },
              {
                "name": "Oklahoma St Cowboys",
                "price": 1.18
              }
            ]
          }
        ]
      }
    ]
  },
  {
    "id": "075eb5d63c2420838ad2b6e9fe5f0ab6",
    "sport_key": "soccer_australia_aleague",
    "sport_title": "A-League",
    "commence_time": "2025-11-28T08:35:00Z",
    "home_team": "Brisbane Roar",
    "away_team": "Melbourne Victory",
    "bookmakers": [
      {
        "key": "winamax_fr",
        "title": "Winamax (FR)",
        "last_update": "2025-11-28T06:09:59Z",
        "markets": [
          {
            "key": "h2h",
            "last_update": "2025-11-28T06:09:59Z",
            "outcomes": [
              {
                "name": "Brisbane Roar",
                "price": 2.3
              },
              {
                "name": "Melbourne Victory",
                "price": 2.5
              },
              {
                "name": "Draw",
                "price": 3.2
              }
            ]
          }
        ]
      },
      {
        "key": "parionssport_fr",
        "title": "Parions Sport (FR)",
        "last_update": "2025-11-28T06:09:44Z",
        "markets": [
          {
            "key": "h2h",
            "last_update": "2025-11-28T06:09:44Z",
            "outcomes": [
              {
                "name": "Brisbane Roar",
                "price": 2.25
              },
              {
                "name": "Melbourne Victory",
                "price": 2.55
              },
              {
                "name": "Draw",
                "price": 3.2
              }
            ]
          }
        ]
      },
      {
        "key": "winamax_de",
        "title": "Winamax (DE)",
        "last_update": "2025-11-28T06:10:17Z",
        "markets": [
          {
            "key": "h2h",
            "last_update": "2025-11-28T06:10:17Z",
            "outcomes": [
              {
                "name": "Brisbane Roar",
                "price": 2.4
              },
              {
                "name": "Melbourne Victory",
                "price": 2.6
              },
              {
                "name": "Draw",
                "price": 3.4
              }
            ]
          }
        ]
      },
      {
        "key": "marathonbet",
        "title": "Marathon Bet",
        "last_update": "2025-11-28T06:10:12Z",
        "markets": [
          {
            "key": "h2h",
            "last_update": "2025-11-28T06:10:12Z",
            "outcomes": [
              {
                "name": "Brisbane Roar",
                "price": 2.43
              },
              {
                "name": "Melbourne Victory",
                "price": 2.73
              },
              {
                "name": "Draw",
                "price": 3.4
              }
            ]
          }
        ]
      },
      {
        "key": "pmu_fr",
        "title": "PMU (FR)",
        "last_update": "2025-11-28T06:10:27Z",
        "markets": [
          {
            "key": "h2h",
            "last_update": "2025-11-28T06:10:27Z",
            "outcomes": [
              {
                "name": "Brisbane Roar",
                "price": 2.35
              },
              {
                "name": "Melbourne Victory",
                "price": 2.65
              },
              {
                "name": "Draw",
                "price": 3.2
              }
            ]
          }
        ]
      },
      {
        "key": "betsson",
        "title": "Betsson",
        "last_update": "2025-11-28T06:09:30Z",
        "markets": [
          {
            "key": "h2h",
            "last_update": "2025-11-28T06:09:30Z",
            "outcomes": [
              {
                "name": "Brisbane Roar",
                "price": 2.38
              },
              {
                "name": "Melbourne Victory",
                "price": 2.78
              },
              {
                "name": "Draw",
                "price": 3.45
              }
            ]
          }
        ]
      },
      {
        "key": "nordicbet",
        "title": "Nordic Bet",
        "last_update": "2025-11-28T06:09:44Z",
        "markets": [
          {
            "key": "h2h",
            "last_update": "2025-11-28T06:09:44Z",
            "outcomes": [
              {
                "name": "Brisbane Roar",
                "price": 2.38
              },
              {
                "name": "Melbourne Victory",
                "price": 2.78
              },
              {
                "name": "Draw",
                "price": 3.45
              }
            ]
          }
        ]
      },
      {
        "key": "betfair_ex_eu",
        "title": "Betfair",
        "last_update": "2025-11-28T06:10:12Z",
        "markets": [
          {
            "key": "h2h",
            "last_update": "2025-11-28T06:10:12Z",
            "outcomes": [
              {
                "name": "Brisbane Roar",
                "price": 2.54
              },
              {
                "name": "Melbourne Victory",
                "price": 2.96
              },
              {
                "name": "Draw",
                "price": 3.6
              }
            ]
          },
          {
            "key": "h2h_lay",
            "last_update": "2025-11-28T06:10:12Z",
            "outcomes": [
              {
                "name": "Brisbane Roar",
                "price": 2.58
              },
              {
                "name": "Melbourne Victory",
                "price": 3
              },
              {
                "name": "Draw",
                "price": 3.65
              }
            ]
          }
        ]
      },
      {
        "key": "coolbet",
        "title": "Coolbet",
        "last_update": "2025-11-28T06:10:27Z",
        "markets": [
          {
            "key": "h2h",
            "last_update": "2025-11-28T06:10:27Z",
            "outcomes": [
              {
                "name": "Brisbane Roar",
                "price": 2.42
              },
              {
                "name": "Melbourne Victory",
                "price": 2.9
              },
              {
                "name": "Draw",
                "price": 3.55
              }
            ]
          }
        ]
      },
      {
        "key": "unibet_nl",
        "title": "Unibet (NL)",
        "last_update": "2025-11-28T06:09:58Z",
        "markets": [
          {
            "key": "h2h",
            "last_update": "2025-11-28T06:09:58Z",
            "outcomes": [
              {
                "name": "Brisbane Roar",
                "price": 2.5
              },
              {
                "name": "Melbourne Victory",
                "price": 2.6
              },
              {
                "name": "Draw",
                "price": 3.4
              }
            ]
          }
        ]
      },
      {
        "key": "unibet_se",
        "title": "Unibet (SE)",
        "last_update": "2025-11-28T06:10:25Z",
        "markets": [
          {
            "key": "h2h",
            "last_update": "2025-11-28T06:10:25Z",
            "outcomes": [
              {
                "name": "Brisbane Roar",
                "price": 2.5
              },
              {
                "name": "Melbourne Victory",
                "price": 2.6
              },
              {
                "name": "Draw",
                "price": 3.4
              }
            ]
          }
        ]
      },
      {
        "key": "leovegas_se",
        "title": "LeoVegas (SE)",
        "last_update": "2025-11-28T06:09:58Z",
        "markets": [
          {
            "key": "h2h",
            "last_update": "2025-11-28T06:09:58Z",
            "outcomes": [
              {
                "name": "Brisbane Roar",
                "price": 2.55
              },
              {
                "name": "Melbourne Victory",
                "price": 2.63
              },
              {
                "name": "Draw",
                "price": 3.45
              }
            ]
          }
        ]
      },
      {
        "key": "gtbets",
        "title": "GTbets",
        "last_update": "2025-11-28T06:10:13Z",
        "markets": [
          {
            "key": "h2h",
            "last_update": "2025-11-28T06:10:13Z",
            "outcomes": [
              {
                "name": "Brisbane Roar",
                "price": 2.47
              },
              {
                "name": "Melbourne Victory",
                "price": 2.74
              },
              {
                "name": "Draw",
                "price": 3.46
              }
            ]
          }
        ]
      },
      {
        "key": "pinnacle",
        "title": "Pinnacle",
        "last_update": "2025-11-28T06:10:11Z",
        "markets": [
          {
            "key": "h2h",
            "last_update": "2025-11-28T06:10:11Z",
            "outcomes": [
              {
                "name": "Brisbane Roar",
                "price": 2.49
              },
              {
                "name": "Melbourne Victory",
                "price": 2.86
              },
              {
                "name": "Draw",
                "price": 3.55
              }
            ]
          }
        ]
      },
      {
        "key": "sport888",
        "title": "888sport",
        "last_update": "2025-11-28T06:09:44Z",
        "markets": [
          {
            "key": "h2h",
            "last_update": "2025-11-28T06:09:44Z",
            "outcomes": [
              {
                "name": "Brisbane Roar",
                "price": 2.5
              },
              {
                "name": "Melbourne Victory",
                "price": 2.62
              },
              {
                "name": "Draw",
                "price": 3.25
              }
            ]
          }
        ]
      },
      {
        "key": "williamhill",
        "title": "William Hill",
        "last_update": "2025-11-28T06:10:26Z",
        "markets": [
          {
            "key": "h2h",
            "last_update": "2025-11-28T06:10:26Z",
            "outcomes": [
              {
                "name": "Brisbane Roar",
                "price": 2.4
              },
              {
                "name": "Melbourne Victory",
                "price": 2.75
              },
              {
                "name": "Draw",
                "price": 3.3
              }
            ]
          }
        ]
      },
      {
        "key": "betonlineag",
        "title": "BetOnline.ag",
        "last_update": "2025-11-28T06:09:58Z",
        "markets": [
          {
            "key": "h2h",
            "last_update": "2025-11-28T06:09:58Z",
            "outcomes": [
              {
                "name": "Brisbane Roar",
                "price": 2.52
              },
              {
                "name": "Melbourne Victory",
                "price": 2.84
              },
              {
                "name": "Draw",
                "price": 3.5
              }
            ]
          }
        ]
      },
      {
        "key": "codere_it",
        "title": "Codere (IT)",
        "last_update": "2025-11-28T06:09:46Z",
        "markets": [
          {
            "key": "h2h",
            "last_update": "2025-11-28T06:09:46Z",
            "outcomes": [
              {
                "name": "Brisbane Roar",
                "price": 2.42
              },
              {
                "name": "Melbourne Victory",
                "price": 2.65
              },
              {
                "name": "Draw",
                "price": 3.35
              }
            ]
          }
        ]
      },
      {
        "key": "matchbook",
        "title": "Matchbook",
        "last_update": "2025-11-28T06:09:59Z",
        "markets": [
          {
            "key": "h2h",
            "last_update": "2025-11-28T06:09:59Z",
            "outcomes": [
              {
                "name": "Brisbane Roar",
                "price": 2.56
              },
              {
                "name": "Melbourne Victory",
                "price": 2.98
              },
              {
                "name": "Draw",
                "price": 3.6
              }
            ]
          },
          {
            "key": "h2h_lay",
            "last_update": "2025-11-28T06:09:59Z",
            "outcomes": [
              {
                "name": "Brisbane Roar",
                "price": 2.58
              },
              {
                "name": "Melbourne Victory",
                "price": 3
              },
              {
                "name": "Draw",
                "price": 3.65
              }
            ]
          }
        ]
      },
      {
        "key": "everygame",
        "title": "Everygame",
        "last_update": "2025-11-28T06:09:03Z",
        "markets": [
          {
            "key": "h2h",
            "last_update": "2025-11-28T06:09:03Z",
            "outcomes": [
              {
                "name": "Brisbane Roar",
                "price": 2.45
              },
              {
                "name": "Melbourne Victory",
                "price": 2.7
              },
              {
                "name": "Draw",
                "price": 3.4
              }
            ]
          }
        ]
      }
    ]
  },
  {
    "id": "7d14f221072dcad97c00896eb4fb91b8",
    "sport_key": "basketball_ncaab",
    "sport_title": "NCAAB",
    "commence_time": "2025-11-28T15:30:39Z",
    "home_team": "Virginia Tech Hokies",
    "away_team": "VCU Rams",
    "bookmakers": [
      {
        "key": "williamhill",
        "title": "William Hill",
        "last_update": "2025-11-28T06:09:57Z",
        "markets": [
          {
            "key": "h2h",
            "last_update": "2025-11-28T06:09:57Z",
            "outcomes": [
              {
                "name": "VCU Rams",
                "price": 1.73
              },
              {
                "name": "Virginia Tech Hokies",
                "price": 2
              }
            ]
          }
        ]
      },
      {
        "key": "betsson",
        "title": "Betsson",
        "last_update": "2025-11-28T06:10:25Z",
        "markets": [
          {
            "key": "h2h",
            "last_update": "2025-11-28T06:10:25Z",
            "outcomes": [
              {
                "name": "VCU Rams",
                "price": 1.8
              },
              {
                "name": "Virginia Tech Hokies",
                "price": 1.94
              }
            ]
          }
        ]
      },
      {
        "key": "sport888",
        "title": "888sport",
        "last_update": "2025-11-28T06:10:25Z",
        "markets": [
          {
            "key": "h2h",
            "last_update": "2025-11-28T06:10:24Z",
            "outcomes": [
              {
                "name": "VCU Rams",
                "price": 1.8
              },
              {
                "name": "Virginia Tech Hokies",
                "price": 2
              }
            ]
          }
        ]
      },
      {
        "key": "nordicbet",
        "title": "Nordic Bet",
        "last_update": "2025-11-28T06:10:13Z",
        "markets": [
          {
            "key": "h2h",
            "last_update": "2025-11-28T06:10:13Z",
            "outcomes": [
              {
                "name": "VCU Rams",
                "price": 1.8
              },
              {
                "name": "Virginia Tech Hokies",
                "price": 1.94
              }
            ]
          }
        ]
      }
    ]
  },
  {
    "id": "a796b0427021a7c8f8c19f505d8fdfbd",
    "sport_key": "icehockey_liiga",
    "sport_title": "Liiga",
    "commence_time": "2025-11-28T16:30:00Z",
    "home_team": "HIFK",
    "away_team": "TPS",
    "bookmakers": [
      {
        "key": "williamhill",
        "title": "William Hill",
        "last_update": "2025-11-28T06:09:26Z",
        "markets": [
          {
            "key": "h2h",
            "last_update": "2025-11-28T06:09:26Z",
            "outcomes": [
              {
                "name": "HIFK",
                "price": 1.91
              },
              {
                "name": "TPS",
                "price": 1.91
              }
            ]
          }
        ]
      },
      {
        "key": "onexbet",
        "title": "1xBet",
        "last_update": "2025-11-28T06:09:25Z",
        "markets": [
          {
            "key": "h2h",
            "last_update": "2025-11-28T06:09:25Z",
            "outcomes": [
              {
                "name": "HIFK",
                "price": 2.43
              },
              {
                "name": "TPS",
                "price": 2.51
              },
              {
                "name": "Draw",
                "price": 3.88
              }
            ]
          }
        ]
      },
      {
        "key": "sport888",
        "title": "888sport",
        "last_update": "2025-11-28T06:10:07Z",
        "markets": [
          {
            "key": "h2h",
            "last_update": "2025-11-28T06:10:07Z",
            "outcomes": [
              {
                "name": "HIFK",
                "price": 1.91
              },
              {
                "name": "TPS",
                "price": 1.91
              }
            ]
          }
        ]
      },
      {
        "key": "betclic_fr",
        "title": "Betclic (FR)",
        "last_update": "2025-11-28T06:08:21Z",
        "markets": [
          {
            "key": "h2h",
            "last_update": "2025-11-28T06:08:21Z",
            "outcomes": [
              {
                "name": "HIFK",
                "price": 2.25
              },
              {
                "name": "TPS",
                "price": 2.33
              },
              {
                "name": "Draw",
                "price": 3.45
              }
            ]
          }
        ]
      },
      {
        "key": "winamax_de",
        "title": "Winamax (DE)",
        "last_update": "2025-11-28T06:09:55Z",
        "markets": [
          {
            "key": "h2h",
            "last_update": "2025-11-28T06:09:55Z",
            "outcomes": [
              {
                "name": "HIFK",
                "price": 2.4
              },
              {
                "name": "TPS",
                "price": 2.4
              },
              {
                "name": "Draw",
                "price": 3.85
              }
            ]
          }
        ]
      },
      {
        "key": "winamax_fr",
        "title": "Winamax (FR)",
        "last_update": "2025-11-28T06:09:31Z",
        "markets": [
          {
            "key": "h2h",
            "last_update": "2025-11-28T06:09:31Z",
            "outcomes": [
              {
                "name": "HIFK",
                "price": 2.2
              },
              {
                "name": "TPS",
                "price": 2.2
              },
              {
                "name": "Draw",
                "price": 3.5
              }
            ]
          }
        ]
      },
      {
        "key": "pinnacle",
        "title": "Pinnacle",
        "last_update": "2025-11-28T06:10:07Z",
        "markets": [
          {
            "key": "h2h",
            "last_update": "2025-11-28T06:10:07Z",
            "outcomes": [
              {
                "name": "HIFK",
                "price": 1.88
              },
              {
                "name": "TPS",
                "price": 1.91
              }
            ]
          }
        ]
      },
      {
        "key": "unibet_se",
        "title": "Unibet (SE)",
        "last_update": "2025-11-28T06:09:25Z",
        "markets": [
          {
            "key": "h2h",
            "last_update": "2025-11-28T06:09:25Z",
            "outcomes": [
              {
                "name": "HIFK",
                "price": 2.45
              },
              {
                "name": "TPS",
                "price": 2.55
              },
              {
                "name": "Draw",
                "price": 3.8
              }
            ]
          }
        ]
      },
      {
        "key": "leovegas_se",
        "title": "LeoVegas (SE)",
        "last_update": "2025-11-28T06:09:39Z",
        "markets": [
          {
            "key": "h2h",
            "last_update": "2025-11-28T06:09:39Z",
            "outcomes": [
              {
                "name": "HIFK",
                "price": 2.55
              },
              {
                "name": "TPS",
                "price": 2.63
              },
              {
                "name": "Draw",
                "price": 3.9
              }
            ]
          }
        ]
      },
      {
        "key": "unibet_nl",
        "title": "Unibet (NL)",
        "last_update": "2025-11-28T06:10:21Z",
        "markets": [
          {
            "key": "h2h",
            "last_update": "2025-11-28T06:10:21Z",
            "outcomes": [
              {
                "name": "HIFK",
                "price": 2.45
              },
              {
                "name": "TPS",
                "price": 2.55
              },
              {
                "name": "Draw",
                "price": 3.8
              }
            ]
          }
        ]
      },
      {
        "key": "coolbet",
        "title": "Coolbet",
        "last_update": "2025-11-28T06:10:08Z",
        "markets": [
          {
            "key": "h2h",
            "last_update": "2025-11-28T06:10:08Z",
            "outcomes": [
              {
                "name": "HIFK",
                "price": 2.45
              },
              {
                "name": "TPS",
                "price": 2.78
              },
              {
                "name": "Draw",
                "price": 3.8
              }
            ]
          }
        ]
      },
      {
        "key": "nordicbet",
        "title": "Nordic Bet",
        "last_update": "2025-11-28T06:10:08Z",
        "markets": [
          {
            "key": "h2h",
            "last_update": "2025-11-28T06:10:08Z",
            "outcomes": [
              {
                "name": "HIFK",
                "price": 1.87
              },
              {
                "name": "TPS",
                "price": 1.98
              }
            ]
          }
        ]
      },
      {
        "key": "betsson",
        "title": "Betsson",
        "last_update": "2025-11-28T06:09:28Z",
        "markets": [
          {
            "key": "h2h",
            "last_update": "2025-11-28T06:09:27Z",
            "outcomes": [
              {
                "name": "HIFK",
                "price": 1.85
              },
              {
                "name": "TPS",
                "price": 1.96
              }
            ]
          }
        ]
      },
      {
        "key": "everygame",
        "title": "Everygame",
        "last_update": "2025-11-28T06:09:41Z",
        "markets": [
          {
            "key": "h2h",
            "last_update": "2025-11-28T06:09:41Z",
            "outcomes": [
              {
                "name": "HIFK",
                "price": 2.4
              },
              {
                "name": "TPS",
                "price": 2.45
              },
              {
                "name": "Draw",
                "price": 3.5
              }
            ]
          }
        ]
      }
    ]
  },
  {
    "id": "efe201151239a728d563cc13f55b9ba7",
    "sport_key": "icehockey_mestis",
    "sport_title": "Mestis",
    "commence_time": "2025-11-28T16:30:00Z",
    "home_team": "Hermes",
    "away_team": "Kiekko-Vantaa",
    "bookmakers": [
      {
        "key": "pinnacle",
        "title": "Pinnacle",
        "last_update": "2025-11-28T06:10:25Z",
        "markets": [
          {
            "key": "h2h",
            "last_update": "2025-11-28T06:10:25Z",
            "outcomes": [
              {
                "name": "Hermes",
                "price": 2.72
              },
              {
                "name": "Kiekko-Vantaa",
                "price": 1.4
              }
            ]
          }
        ]
      },
      {
        "key": "onexbet",
        "title": "1xBet",
        "last_update": "2025-11-28T06:10:21Z",
        "markets": [
          {
            "key": "h2h",
            "last_update": "2025-11-28T06:10:21Z",
            "outcomes": [
              {
                "name": "Hermes",
                "price": 3.5
              },
              {
                "name": "Kiekko-Vantaa",
                "price": 1.75
              },
              {
                "name": "Draw",
                "price": 4.33
              }
            ]
          }
        ]
      },
      {
        "key": "betsson",
        "title": "Betsson",
        "last_update": "2025-11-28T06:09:29Z",
        "markets": [
          {
            "key": "h2h",
            "last_update": "2025-11-28T06:09:29Z",
            "outcomes": [
              {
                "name": "Hermes",
                "price": 2.65
              },
              {
                "name": "Kiekko-Vantaa",
                "price": 1.44
              }
            ]
          }
        ]
      },
      {
        "key": "nordicbet",
        "title": "Nordic Bet",
        "last_update": "2025-11-28T06:08:59Z",
        "markets": [
          {
            "key": "h2h",
            "last_update": "2025-11-28T06:08:59Z",
            "outcomes": [
              {
                "name": "Hermes",
                "price": 2.65
              },
              {
                "name": "Kiekko-Vantaa",
                "price": 1.44
              }
            ]
          }
        ]
      },
      {
        "key": "leovegas_se",
        "title": "LeoVegas (SE)",
        "last_update": "2025-11-28T06:09:40Z",
        "markets": [
          {
            "key": "h2h",
            "last_update": "2025-11-28T06:09:40Z",
            "outcomes": [
              {
                "name": "Hermes",
                "price": 3.3
              },
              {
                "name": "Kiekko-Vantaa",
                "price": 1.83
              },
              {
                "name": "Draw",
                "price": 4.2
              }
            ]
          }
        ]
      },
      {
        "key": "unibet_se",
        "title": "Unibet (SE)",
        "last_update": "2025-11-28T06:10:11Z",
        "markets": [
          {
            "key": "h2h",
            "last_update": "2025-11-28T06:10:11Z",
            "outcomes": [
              {
                "name": "Hermes",
                "price": 3.3
              },
              {
                "name": "Kiekko-Vantaa",
                "price": 1.83
              },
              {
                "name": "Draw",
                "price": 4.2
              }
            ]
          }
        ]
      },
      {
        "key": "unibet_nl",
        "title": "Unibet (NL)",
        "last_update": "2025-11-28T06:09:40Z",
        "markets": [
          {
            "key": "h2h",
            "last_update": "2025-11-28T06:09:40Z",
            "outcomes": [
              {
                "name": "Hermes",
                "price": 3.3
              },
              {
                "name": "Kiekko-Vantaa",
                "price": 1.83
              },
              {
                "name": "Draw",
                "price": 4.2
              }
            ]
          }
        ]
      }
    ]
  },
  {
    "id": "6d85fddcc8968ccab92c7692778957be",
    "sport_key": "icehockey_liiga",
    "sport_title": "Liiga",
    "commence_time": "2025-11-28T16:30:00Z",
    "home_team": "JYP",
    "away_team": "SaiPa",
    "bookmakers": [
      {
        "key": "pinnacle",
        "title": "Pinnacle",
        "last_update": "2025-11-28T06:10:07Z",
        "markets": [
          {
            "key": "h2h",
            "last_update": "2025-11-28T06:10:07Z",
            "outcomes": [
              {
                "name": "JYP",
                "price": 1.7
              },
              {
                "name": "SaiPa",
                "price": 2.13
              }
            ]
          }
        ]
      },
      {
        "key": "winamax_fr",
        "title": "Winamax (FR)",
        "last_update": "2025-11-28T06:09:31Z",
        "markets": [
          {
            "key": "h2h",
            "last_update": "2025-11-28T06:09:31Z",
            "outcomes": [
              {
                "name": "JYP",
                "price": 1.94
              },
              {
                "name": "SaiPa",
                "price": 2.5
              },
              {
                "name": "Draw",
                "price": 3.65
              }
            ]
          }
        ]
      },
      {
        "key": "williamhill",
        "title": "William Hill",
        "last_update": "2025-11-28T06:09:26Z",
        "markets": [
          {
            "key": "h2h",
            "last_update": "2025-11-28T06:09:26Z",
            "outcomes": [
              {
                "name": "JYP",
                "price": 1.73
              },
              {
                "name": "SaiPa",
                "price": 2.1
              }
            ]
          }
        ]
      },
      {
        "key": "parionssport_fr",
        "title": "Parions Sport (FR)",
        "last_update": "2025-11-28T06:09:39Z",
        "markets": [
          {
            "key": "h2h",
            "last_update": "2025-11-28T06:09:39Z",
            "outcomes": [
              {
                "name": "JYP",
                "price": 1.97
              },
              {
                "name": "SaiPa",
                "price": 2.55
              },
              {
                "name": "Draw",
                "price": 3.65
              }
            ]
          }
        ]
      },
      {
        "key": "sport888",
        "title": "888sport",
        "last_update": "2025-11-28T06:10:07Z",
        "markets": [
          {
            "key": "h2h",
            "last_update": "2025-11-28T06:10:07Z",
            "outcomes": [
              {
                "name": "JYP",
                "price": 1.73
              },
              {
                "name": "SaiPa",
                "price": 2.1
              }
            ]
          }
        ]
      },
      {
        "key": "betclic_fr",
        "title": "Betclic (FR)",
        "last_update": "2025-11-28T06:08:21Z",
        "markets": [
          {
            "key": "h2h",
            "last_update": "2025-11-28T06:08:21Z",
            "outcomes": [
              {
                "name": "JYP",
                "price": 1.98
              },
              {
                "name": "SaiPa",
                "price": 2.6
              },
              {
                "name": "Draw",
                "price": 3.7
              }
            ]
          }
        ]
      },
      {
        "key": "onexbet",
        "title": "1xBet",
        "last_update": "2025-11-28T06:09:25Z",
        "markets": [
          {
            "key": "h2h",
            "last_update": "2025-11-28T06:09:25Z",
            "outcomes": [
              {
                "name": "JYP",
                "price": 2.1
              },
              {
                "name": "SaiPa",
                "price": 2.85
              },
              {
                "name": "Draw",
                "price": 4.25
              }
            ]
          }
        ]
      },
      {
        "key": "winamax_de",
        "title": "Winamax (DE)",
        "last_update": "2025-11-28T06:09:55Z",
        "markets": [
          {
            "key": "h2h",
            "last_update": "2025-11-28T06:09:55Z",
            "outcomes": [
              {
                "name": "JYP",
                "price": 2.05
              },
              {
                "name": "SaiPa",
                "price": 2.75
              },
              {
                "name": "Draw",
                "price": 4
              }
            ]
          }
        ]
      },
      {
        "key": "unibet_nl",
        "title": "Unibet (NL)",
        "last_update": "2025-11-28T06:10:21Z",
        "markets": [
          {
            "key": "h2h",
            "last_update": "2025-11-28T06:10:21Z",
            "outcomes": [
              {
                "name": "JYP",
                "price": 2.12
              },
              {
                "name": "SaiPa",
                "price": 2.88
              },
              {
                "name": "Draw",
                "price": 4.1
              }
            ]
          }
        ]
      },
      {
        "key": "unibet_se",
        "title": "Unibet (SE)",
        "last_update": "2025-11-28T06:09:25Z",
        "markets": [
          {
            "key": "h2h",
            "last_update": "2025-11-28T06:09:25Z",
            "outcomes": [
              {
                "name": "JYP",
                "price": 2.12
              },
              {
                "name": "SaiPa",
                "price": 2.88
              },
              {
                "name": "Draw",
                "price": 4.1
              }
            ]
          }
        ]
      },
      {
        "key": "leovegas_se",
        "title": "LeoVegas (SE)",
        "last_update": "2025-11-28T06:09:39Z",
        "markets": [
          {
            "key": "h2h",
            "last_update": "2025-11-28T06:09:39Z",
            "outcomes": [
              {
                "name": "JYP",
                "price": 2.18
              },
              {
                "name": "SaiPa",
                "price": 2.95
              },
              {
                "name": "Draw",
                "price": 4.2
              }
            ]
          }
        ]
      },
      {
        "key": "tipico_de",
        "title": "Tipico",
        "last_update": "2025-11-28T06:09:41Z",
        "markets": [
          {
            "key": "h2h",
            "last_update": "2025-11-28T06:09:41Z",
            "outcomes": [
              {
                "name": "JYP",
                "price": 2.05
              },
              {
                "name": "SaiPa",
                "price": 2.8
              },
              {
                "name": "Draw",
                "price": 4.1
              }
            ]
          }
        ]
      },
      {
        "key": "coolbet",
        "title": "Coolbet",
        "last_update": "2025-11-28T06:10:08Z",
        "markets": [
          {
            "key": "h2h",
            "last_update": "2025-11-28T06:10:08Z",
            "outcomes": [
              {
                "name": "JYP",
                "price": 2.33
              },
              {
                "name": "SaiPa",
                "price": 2.87
              },
              {
                "name": "Draw",
                "price": 3.95
              }
            ]
          }
        ]
      },
      {
        "key": "nordicbet",
        "title": "Nordic Bet",
        "last_update": "2025-11-28T06:10:08Z",
        "markets": [
          {
            "key": "h2h",
            "last_update": "2025-11-28T06:10:08Z",
            "outcomes": [
              {
                "name": "JYP",
                "price": 1.74
              },
              {
                "name": "SaiPa",
                "price": 2.15
              }
            ]
          }
        ]
      },
      {
        "key": "betsson",
        "title": "Betsson",
        "last_update": "2025-11-28T06:09:28Z",
        "markets": [
          {
            "key": "h2h",
            "last_update": "2025-11-28T06:09:28Z",
            "outcomes": [
              {
                "name": "JYP",
                "price": 1.72
              },
              {
                "name": "SaiPa",
                "price": 2.12
              }
            ]
          }
        ]
      },
      {
        "key": "everygame",
        "title": "Everygame",
        "last_update": "2025-11-28T06:09:41Z",
        "markets": [
          {
            "key": "h2h",
            "last_update": "2025-11-28T06:09:41Z",
            "outcomes": [
              {
                "name": "JYP",
                "price": 2.1
              },
              {
                "name": "SaiPa",
                "price": 2.7
              },
              {
                "name": "Draw",
                "price": 3.85
              }
            ]
          }
        ]
      }
    ]
  },
  {
    "id": "50f60ddb3c8dceb8abb8f7c38cb932bd",
    "sport_key": "icehockey_mestis",
    "sport_title": "Mestis",
    "commence_time": "2025-11-28T16:30:00Z",
    "home_team": "JoKP",
    "away_team": "Pyry",
    "bookmakers": [
      {
        "key": "pinnacle",
        "title": "Pinnacle",
        "last_update": "2025-11-28T06:10:25Z",
        "markets": [
          {
            "key": "h2h",
            "last_update": "2025-11-28T06:10:25Z",
            "outcomes": [
              {
                "name": "JoKP",
                "price": 1.2
              },
              {
                "name": "Pyry",
                "price": 3.88
              }
            ]
          }
        ]
      },
      {
        "key": "betsson",
        "title": "Betsson",
        "last_update": "2025-11-28T06:09:29Z",
        "markets": [
          {
            "key": "h2h",
            "last_update": "2025-11-28T06:09:29Z",
            "outcomes": [
              {
                "name": "JoKP",
                "price": 1.23
              },
              {
                "name": "Pyry",
                "price": 3.9
              }
            ]
          }
        ]
      },
      {
        "key": "nordicbet",
        "title": "Nordic Bet",
        "last_update": "2025-11-28T06:08:59Z",
        "markets": [
          {
            "key": "h2h",
            "last_update": "2025-11-28T06:08:59Z",
            "outcomes": [
              {
                "name": "JoKP",
                "price": 1.23
              },
              {
                "name": "Pyry",
                "price": 3.9
              }
            ]
          }
        ]
      },
      {
        "key": "leovegas_se",
        "title": "LeoVegas (SE)",
        "last_update": "2025-11-28T06:09:40Z",
        "markets": [
          {
            "key": "h2h",
            "last_update": "2025-11-28T06:09:40Z",
            "outcomes": [
              {
                "name": "JoKP",
                "price": 1.36
              },
              {
                "name": "Pyry",
                "price": 5.4
              },
              {
                "name": "Draw",
                "price": 6.1
              }
            ]
          }
        ]
      },
      {
        "key": "unibet_se",
        "title": "Unibet (SE)",
        "last_update": "2025-11-28T06:10:11Z",
        "markets": [
          {
            "key": "h2h",
            "last_update": "2025-11-28T06:10:11Z",
            "outcomes": [
              {
                "name": "JoKP",
                "price": 1.36
              },
              {
                "name": "Pyry",
                "price": 5.4
              },
              {
                "name": "Draw",
                "price": 6.1
              }
            ]
          }
        ]
      },
      {
        "key": "unibet_nl",
        "title": "Unibet (NL)",
        "last_update": "2025-11-28T06:09:40Z",
        "markets": [
          {
            "key": "h2h",
            "last_update": "2025-11-28T06:09:40Z",
            "outcomes": [
              {
                "name": "JoKP",
                "price": 1.36
              },
              {
                "name": "Pyry",
                "price": 5.4
              },
              {
                "name": "Draw",
                "price": 6.1
              }
            ]
          }
        ]
      }
    ]
  },
  {
    "id": "be2688396919289849947ecd8623c427",
    "sport_key": "icehockey_liiga",
    "sport_title": "Liiga",
    "commence_time": "2025-11-28T16:30:00Z",
    "home_team": "Lukko",
    "away_team": "Jukurit",
    "bookmakers": [
      {
        "key": "williamhill",
        "title": "William Hill",
        "last_update": "2025-11-28T06:09:26Z",
        "markets": [
          {
            "key": "h2h",
            "last_update": "2025-11-28T06:09:26Z",
            "outcomes": [
              {
                "name": "Jukurit",
                "price": 3.1
              },
              {
                "name": "Lukko",
                "price": 1.36
              }
            ]
          }
        ]
      },
      {
        "key": "onexbet",
        "title": "1xBet",
        "last_update": "2025-11-28T06:09:25Z",
        "markets": [
          {
            "key": "h2h",
            "last_update": "2025-11-28T06:09:25Z",
            "outcomes": [
              {
                "name": "Jukurit",
                "price": 4.33
              },
              {
                "name": "Lukko",
                "price": 1.64
              },
              {
                "name": "Draw",
                "price": 4.5
              }
            ]
          }
        ]
      },
      {
        "key": "sport888",
        "title": "888sport",
        "last_update": "2025-11-28T06:10:07Z",
        "markets": [
          {
            "key": "h2h",
            "last_update": "2025-11-28T06:10:07Z",
            "outcomes": [
              {
                "name": "Jukurit",
                "price": 3.1
              },
              {
                "name": "Lukko",
                "price": 1.36
              }
            ]
          }
        ]
      },
      {
        "key": "parionssport_fr",
        "title": "Parions Sport (FR)",
        "last_update": "2025-11-28T06:09:39Z",
        "markets": [
          {
            "key": "h2h",
            "last_update": "2025-11-28T06:09:39Z",
            "outcomes": [
              {
                "name": "Jukurit",
                "price": 3.85
              },
              {
                "name": "Lukko",
                "price": 1.52
              },
              {
                "name": "Draw",
                "price": 4
              }
            ]
          }
        ]
      },
      {
        "key": "betclic_fr",
        "title": "Betclic (FR)",
        "last_update": "2025-11-28T06:08:21Z",
        "markets": [
          {
            "key": "h2h",
            "last_update": "2025-11-28T06:08:21Z",
            "outcomes": [
              {
                "name": "Jukurit",
                "price": 3.9
              },
              {
                "name": "Lukko",
                "price": 1.53
              },
              {
                "name": "Draw",
                "price": 4.05
              }
            ]
          }
        ]
      },
      {
        "key": "winamax_de",
        "title": "Winamax (DE)",
        "last_update": "2025-11-28T06:09:55Z",
        "markets": [
          {
            "key": "h2h",
            "last_update": "2025-11-28T06:09:55Z",
            "outcomes": [
              {
                "name": "Jukurit",
                "price": 4.2
              },
              {
                "name": "Lukko",
                "price": 1.58
              },
              {
                "name": "Draw",
                "price": 4.5
              }
            ]
          }
        ]
      },
      {
        "key": "winamax_fr",
        "title": "Winamax (FR)",
        "last_update": "2025-11-28T06:09:31Z",
        "markets": [
          {
            "key": "h2h",
            "last_update": "2025-11-28T06:09:31Z",
            "outcomes": [
              {
                "name": "Jukurit",
                "price": 3.85
              },
              {
                "name": "Lukko",
                "price": 1.5
              },
              {
                "name": "Draw",
                "price": 4
              }
            ]
          }
        ]
      },
      {
        "key": "pinnacle",
        "title": "Pinnacle",
        "last_update": "2025-11-28T06:10:07Z",
        "markets": [
          {
            "key": "h2h",
            "last_update": "2025-11-28T06:10:07Z",
            "outcomes": [
              {
                "name": "Jukurit",
                "price": 3.28
              },
              {
                "name": "Lukko",
                "price": 1.31
              }
            ]
          }
        ]
      },
      {
        "key": "unibet_se",
        "title": "Unibet (SE)",
        "last_update": "2025-11-28T06:09:25Z",
        "markets": [
          {
            "key": "h2h",
            "last_update": "2025-11-28T06:09:25Z",
            "outcomes": [
              {
                "name": "Jukurit",
                "price": 4.6
              },
              {
                "name": "Lukko",
                "price": 1.57
              },
              {
                "name": "Draw",
                "price": 4.5
              }
            ]
          }
        ]
      },
      {
        "key": "leovegas_se",
        "title": "LeoVegas (SE)",
        "last_update": "2025-11-28T06:09:39Z",
        "markets": [
          {
            "key": "h2h",
            "last_update": "2025-11-28T06:09:39Z",
            "outcomes": [
              {
                "name": "Jukurit",
                "price": 4.8
              },
              {
                "name": "Lukko",
                "price": 1.64
              },
              {
                "name": "Draw",
                "price": 4.7
              }
            ]
          }
        ]
      },
      {
        "key": "unibet_nl",
        "title": "Unibet (NL)",
        "last_update": "2025-11-28T06:10:21Z",
        "markets": [
          {
            "key": "h2h",
            "last_update": "2025-11-28T06:10:21Z",
            "outcomes": [
              {
                "name": "Jukurit",
                "price": 4.6
              },
              {
                "name": "Lukko",
                "price": 1.57
              },
              {
                "name": "Draw",
                "price": 4.5
              }
            ]
          }
        ]
      },
      {
        "key": "tipico_de",
        "title": "Tipico",
        "last_update": "2025-11-28T06:09:41Z",
        "markets": [
          {
            "key": "h2h",
            "last_update": "2025-11-28T06:09:41Z",
            "outcomes": [
              {
                "name": "Jukurit",
                "price": 4.4
              },
              {
                "name": "Lukko",
                "price": 1.57
              },
              {
                "name": "Draw",
                "price": 4.5
              }
            ]
          }
        ]
      },
      {
        "key": "coolbet",
        "title": "Coolbet",
        "last_update": "2025-11-28T06:10:08Z",
        "markets": [
          {
            "key": "h2h",
            "last_update": "2025-11-28T06:10:08Z",
            "outcomes": [
              {
                "name": "Jukurit",
                "price": 5.15
              },
              {
                "name": "Lukko",
                "price": 1.63
              },
              {
                "name": "Draw",
                "price": 4.5
              }
            ]
          }
        ]
      },
      {
        "key": "nordicbet",
        "title": "Nordic Bet",
        "last_update": "2025-11-28T06:10:08Z",
        "markets": [
          {
            "key": "h2h",
            "last_update": "2025-11-28T06:10:08Z",
            "outcomes": [
              {
                "name": "Jukurit",
                "price": 3.45
              },
              {
                "name": "Lukko",
                "price": 1.33
              }
            ]
          }
        ]
      },
      {
        "key": "betsson",
        "title": "Betsson",
        "last_update": "2025-11-28T06:09:28Z",
        "markets": [
          {
            "key": "h2h",
            "last_update": "2025-11-28T06:09:28Z",
            "outcomes": [
              {
                "name": "Jukurit",
                "price": 3.4
              },
              {
                "name": "Lukko",
                "price": 1.32
              }
            ]
          }
        ]
      },
      {
        "key": "everygame",
        "title": "Everygame",
        "last_update": "2025-11-28T06:09:41Z",
        "markets": [
          {
            "key": "h2h",
            "last_update": "2025-11-28T06:09:41Z",
            "outcomes": [
              {
                "name": "Jukurit",
                "price": 4.5
              },
              {
                "name": "Lukko",
                "price": 1.57
              },
              {
                "name": "Draw",
                "price": 4
              }
            ]
          }
        ]
      }
    ]
  },
  {
    "id": "c74d22bbe8d73b6688c90f916c1cc2b2",
    "sport_key": "icehockey_liiga",
    "sport_title": "Liiga",
    "commence_time": "2025-11-28T16:30:00Z",
    "home_team": "sst",
    "away_team": "KalPa",
    "bookmakers": [
      {
        "key": "betclic_fr",
        "title": "Betclic (FR)",
        "last_update": "2025-11-28T06:08:21Z",
        "markets": [
          {
            "key": "h2h",
            "last_update": "2025-11-28T06:08:21Z",
            "outcomes": [
              {
                "name": "KalPa",
                "price": 2.43
              },
              {
                "name": "sst",
                "price": 2.15
              },
              {
                "name": "Draw",
                "price": 3.5
              }
            ]
          }
        ]
      },
      {
        "key": "onexbet",
        "title": "1xBet",
        "last_update": "2025-11-28T06:09:25Z",
        "markets": [
          {
            "key": "h2h",
            "last_update": "2025-11-28T06:09:25Z",
            "outcomes": [
              {
                "name": "KalPa",
                "price": 2.69
              },
              {
                "name": "sst",
                "price": 2.24
              },
              {
                "name": "Draw",
                "price": 4.1
              }
            ]
          }
        ]
      },
      {
        "key": "parionssport_fr",
        "title": "Parions Sport (FR)",
        "last_update": "2025-11-28T06:09:39Z",
        "markets": [
          {
            "key": "h2h",
            "last_update": "2025-11-28T06:09:39Z",
            "outcomes": [
              {
                "name": "KalPa",
                "price": 2.4
              },
              {
                "name": "sst",
                "price": 2.15
              },
              {
                "name": "Draw",
                "price": 3.5
              }
            ]
          }
        ]
      },
      {
        "key": "williamhill",
        "title": "William Hill",
        "last_update": "2025-11-28T06:09:26Z",
        "markets": [
          {
            "key": "h2h",
            "last_update": "2025-11-28T06:09:26Z",
            "outcomes": [
              {
                "name": "KalPa",
                "price": 2
              },
              {
                "name": "sst",
                "price": 1.8
              }
            ]
          }
        ]
      },
      {
        "key": "sport888",
        "title": "888sport",
        "last_update": "2025-11-28T06:10:07Z",
        "markets": [
          {
            "key": "h2h",
            "last_update": "2025-11-28T06:10:07Z",
            "outcomes": [
              {
                "name": "KalPa",
                "price": 2
              },
              {
                "name": "sst",
                "price": 1.8
              }
            ]
          }
        ]
      },
      {
        "key": "pinnacle",
        "title": "Pinnacle",
        "last_update": "2025-11-28T06:10:07Z",
        "markets": [
          {
            "key": "h2h",
            "last_update": "2025-11-28T06:10:07Z",
            "outcomes": [
              {
                "name": "KalPa",
                "price": 2.12
              },
              {
                "name": "sst",
                "price": 1.7
              }
            ]
          }
        ]
      },
      {
        "key": "winamax_de",
        "title": "Winamax (DE)",
        "last_update": "2025-11-28T06:09:55Z",
        "markets": [
          {
            "key": "h2h",
            "last_update": "2025-11-28T06:09:55Z",
            "outcomes": [
              {
                "name": "KalPa",
                "price": 2.55
              },
              {
                "name": "sst",
                "price": 2.25
              },
              {
                "name": "Draw",
                "price": 3.85
              }
            ]
          }
        ]
      },
      {
        "key": "winamax_fr",
        "title": "Winamax (FR)",
        "last_update": "2025-11-28T06:09:31Z",
        "markets": [
          {
            "key": "h2h",
            "last_update": "2025-11-28T06:09:31Z",
            "outcomes": [
              {
                "name": "KalPa",
                "price": 2.35
              },
              {
                "name": "sst",
                "price": 2.1
              },
              {
                "name": "Draw",
                "price": 3.5
              }
            ]
          }
        ]
      },
      {
        "key": "tipico_de",
        "title": "Tipico",
        "last_update": "2025-11-28T06:09:41Z",
        "markets": [
          {
            "key": "h2h",
            "last_update": "2025-11-28T06:09:41Z",
            "outcomes": [
              {
                "name": "KalPa",
                "price": 2.65
              },
              {
                "name": "sst",
                "price": 2.2
              },
              {
                "name": "Draw",
                "price": 3.9
              }
            ]
          }
        ]
      },
      {
        "key": "nordicbet",
        "title": "Nordic Bet",
        "last_update": "2025-11-28T06:10:08Z",
        "markets": [
          {
            "key": "h2h",
            "last_update": "2025-11-28T06:10:08Z",
            "outcomes": [
              {
                "name": "KalPa",
                "price": 2.03
              },
              {
                "name": "sst",
                "price": 1.82
              }
            ]
          }
        ]
      },
      {
        "key": "betsson",
        "title": "Betsson",
        "last_update": "2025-11-28T06:09:28Z",
        "markets": [
          {
            "key": "h2h",
            "last_update": "2025-11-28T06:09:28Z",
            "outcomes": [
              {
                "name": "KalPa",
                "price": 2.01
              },
              {
                "name": "sst",
                "price": 1.8
              }
            ]
          }
        ]
      },
      {
        "key": "unibet_se",
        "title": "Unibet (SE)",
        "last_update": "2025-11-28T06:09:25Z",
        "markets": [
          {
            "key": "h2h",
            "last_update": "2025-11-28T06:09:25Z",
            "outcomes": [
              {
                "name": "KalPa",
                "price": 2.65
              },
              {
                "name": "sst",
                "price": 2.4
              },
              {
                "name": "Draw",
                "price": 3.7
              }
            ]
          }
        ]
      },
      {
        "key": "leovegas_se",
        "title": "LeoVegas (SE)",
        "last_update": "2025-11-28T06:09:39Z",
        "markets": [
          {
            "key": "h2h",
            "last_update": "2025-11-28T06:09:39Z",
            "outcomes": [
              {
                "name": "KalPa",
                "price": 2.75
              },
              {
                "name": "sst",
                "price": 2.48
              },
              {
                "name": "Draw",
                "price": 3.8
              }
            ]
          }
        ]
      },
      {
        "key": "unibet_nl",
        "title": "Unibet (NL)",
        "last_update": "2025-11-28T06:10:21Z",
        "markets": [
          {
            "key": "h2h",
            "last_update": "2025-11-28T06:10:21Z",
            "outcomes": [
              {
                "name": "KalPa",
                "price": 2.65
              },
              {
                "name": "sst",
                "price": 2.4
              },
              {
                "name": "Draw",
                "price": 3.7
              }
            ]
          }
        ]
      },
      {
        "key": "coolbet",
        "title": "Coolbet",
        "last_update": "2025-11-28T06:10:08Z",
        "markets": [
          {
            "key": "h2h",
            "last_update": "2025-11-28T06:10:08Z",
            "outcomes": [
              {
                "name": "KalPa",
                "price": 2.85
              },
              {
                "name": "sst",
                "price": 2.4
              },
              {
                "name": "Draw",
                "price": 3.8
              }
            ]
          }
        ]
      },
      {
        "key": "everygame",
        "title": "Everygame",
        "last_update": "2025-11-28T06:09:41Z",
        "markets": [
          {
            "key": "h2h",
            "last_update": "2025-11-28T06:09:41Z",
            "outcomes": [
              {
                "name": "KalPa",
                "price": 2.75
              },
              {
                "name": "sst",
                "price": 2.1
              },
              {
                "name": "Draw",
                "price": 3.65
              }
            ]
          }
        ]
      }
    ]
  }
]